{
  "wrapper": "div.wrapper-content",
  "sections": {
    "banner1": {
      "type": "home-custom-block-baner-collection-list",
      "blocks": {
        "4240db2e-06bb-4f9f-94f5-cb306e322c75": {
          "type": "largeImg",
          "settings": {
            "collection_page": "",
            "image": "shopify:\/\/shop_images\/ATF_Banner_2.png",
            "display_parallax": false,
            "dpl_down_arrow": false,
            "height_img_parallax": "970px",
            "alignment": "left",
            "banner_heading": "Metropólis",
            "font_size_banner_heading": "40px",
            "color_banner_heading": "#232323",
            "banner_des": "Pellentesque posuere orci lobortis scelerisque blandit. Donec id tellus lacinia an tincidunt risus an consequat delit quisquemos.",
            "font_size_banner_des": "12px",
            "color_banner_des": "#232323",
            "countdown": "",
            "banner_button": "Shop The Looks",
            "link": "",
            "bg_banner_button": "#232323",
            "border_banner_button": "#232323",
            "color_banner_button": "#fff",
            "min_width_banner_button": "167px"
          }
        }
      },
      "block_order": [
        "4240db2e-06bb-4f9f-94f5-cb306e322c75"
      ],
      "settings": {
        "layout": "default",
        "margin_bottom_mb": 25,
        "margin_bottom_tab": 30,
        "margin_bottom": 30
      }
    },
    "banner2": {
      "type": "home-custom-product-collection-list",
      "settings": {
        "slider_collection_limit": 5,
        "bg_collection_button": "#fff",
        "border_collection_button": "#dadada",
        "color_collection_button": "#27221b",
        "min_width_collection_button": "252px",
        "margin_bottom_mb": 40,
        "margin_bottom_tab": 40,
        "margin_bottom": 0
      }
    }
  },
  "order": [
    "banner1",
    "banner2"
  ]
}